pytest_isolate/__about__.py
pytest_isolate/__init__.py
pytest_isolate/plugin.py
pytest_isolate/resource_management.py
pytest_isolate/tracing.py
pytest_isolate-0.0.12.dist-info/METADATA
pytest_isolate-0.0.12.dist-info/WHEEL
pytest_isolate-0.0.12.dist-info/entry_points.txt
pytest_isolate-0.0.12.dist-info/licenses/LICENSE.txt
pytest_isolate-0.0.12.dist-info/RECORD
