Metadata-Version: 2.4
Name: pytest-isolate
Version: 0.0.12
Summary: Run pytest tests in isolated subprocesses 
Project-URL: Documentation, https://github.com/gilfree/pytest-isolate#readme
Project-URL: Issues, https://github.com/gilfree/pytest-isolate/issues
Project-URL: Source, https://github.com/gilfree/pytest-isolate
Author-email: gilfree <gilfree@users.noreply.github.com>
License-Expression: MIT
License-File: LICENSE.txt
Classifier: Development Status :: 4 - Beta
Classifier: Operating System :: POSIX
Classifier: Programming Language :: Python
Classifier: Programming Language :: Python :: 3.9
Classifier: Programming Language :: Python :: 3.10
Classifier: Programming Language :: Python :: 3.11
Classifier: Programming Language :: Python :: 3.12
Classifier: Programming Language :: Python :: Implementation :: CPython
Classifier: Programming Language :: Python :: Implementation :: PyPy
Requires-Python: >=3.7
Requires-Dist: dill
Requires-Dist: filelock
Requires-Dist: pytest
Requires-Dist: tblib
Provides-Extra: gpu
Requires-Dist: pynvml; extra == 'gpu'
